<?xml version="1.0" encoding="UTF-8" standalone="yes"?>
 <items>
 <item>
<title>[COLOR silver][B]  Próxima Parada - Natal  [/COLOR][/B][COLOR BLUE]  FULL HD  [B][/COLOR][/B]</title>
<link>plugin://plugin.video.elementum/play?uri=magnet:?xt=urn:btih:UU3YMJLA22D54ZFJTLN4KAHJRDV2IHJE</link>
<thumbnail>https://abutretorrents.com/imagens/proxima-parada-natal-download-torrent-2022-dublado-dual-audio-bluray-1080p-720p-4k-hd.jpg</thumbnail>
<fanart></fanart>
<info>Angie se pergunta como seria sua vida se ela tivesse se casado com um ex-namorado que se tornou um famoso locutor esportivo. Ela pega o trem para casa para passar o Natal com sua família e inexplicavelmente se encontra 10 anos no passado. Com o conselho do enigmático condutor do trem, Angie tem a chance de revisitar aquele Natal e aprender o que - e quem - é realmente importante para ela.</info>
</item> 

   
    <item>
<title>[COLOR silver][B]   A GESTORA  [/COLOR][/B]</title>
<link>plugin://plugin.video.elementum/play?uri=magnet:?xt=urn:btih:6a5c2ac94cabf3c7623ad957abbeb3355108d7c5</link>
<thumbnail>https://www.themoviedb.org/t/p/w600_and_h900_bestv2/hRqvE6dABictKuLwqQMzq6AptiZ.jpg</thumbnail>
<fanart></fanart>
<info>Uma jovem ambiciosa faz um acordo inusitado com a chefe. Mas quando começam a surgir dúvidas, pode ser tarde demais para voltar atrás.</info>
</item> 
  
  
   <item>
<title>[COLOR silver][B] [/COLOR][/B]</title>
<link>plugin://plugin.video.elementum/play?uri=</link>
<thumbnail></thumbnail>
<fanart></fanart>
<info></info>
</item> 
  
  
   <item>
<title>[COLOR silver][B] [/COLOR][/B]</title>
<link>plugin://plugin.video.elementum/play?uri=</link>
<thumbnail></thumbnail>
<fanart></fanart>
<info></info>
</item> 
   
   
   
    <item>
<title>[COLOR silver][B] [/COLOR][/B]</title>
<link>plugin://plugin.video.elementum/play?uri=</link>
<thumbnail></thumbnail>
<fanart></fanart>
<info></info>
</item> 
   
   
   
   
   
   
   
   
   
   
</items>
